slg_ff_helpers/__init__.py
slg_ff_helpers/transaction_trends.py
slg_ff_helpers-0.2.0.data/scripts/ff-trend-tracker
slg_ff_helpers-0.2.0.dist-info/METADATA
slg_ff_helpers-0.2.0.dist-info/WHEEL
slg_ff_helpers-0.2.0.dist-info/top_level.txt
slg_ff_helpers-0.2.0.dist-info/RECORD
