Metadata-Version: 2.1
Name: slg-ff-helpers
Version: 0.2.0
Summary: This is a description.
Home-page: UNKNOWN
License: UNKNOWN
Platform: UNKNOWN
Requires-Python: >=3.6.3
